cooplot/__init__.py
cooplot/aggregate.py
cooplot/api.py
cooplot/build.py
cooplot/io.py
cooplot/metrics.py
cooplot/scrape.py
cooplot/viz.py
cooplot-0.1.1.dist-info/METADATA
cooplot-0.1.1.dist-info/WHEEL
cooplot-0.1.1.dist-info/RECORD
