Metadata-Version: 2.4
Name: cooplot
Version: 0.1.1
Summary: Co-op between members and subgroups.
Requires-Python: >=3.10.0
Requires-Dist: matplotlib>=3.10.6
Requires-Dist: mne-connectivity>=0.7.0
Requires-Dist: numpy>=2.2.6
Requires-Dist: python-dotenv>=1.0
Requires-Dist: requests>=2.32.5
Requires-Dist: scholarly>=1.7.11
Requires-Dist: tqdm>=4.67.1
Provides-Extra: dev
Requires-Dist: maturin; extra == 'dev'
Requires-Dist: pytest; extra == 'dev'
Requires-Dist: ruff; extra == 'dev'
Requires-Dist: twine; extra == 'dev'
